pybloomfilter.cpython-313-darwin.so
pybloomfiltermmap3-0.6.3.dist-info/licenses/LICENSE
pybloomfiltermmap3-0.6.3.dist-info/METADATA
pybloomfiltermmap3-0.6.3.dist-info/WHEEL
pybloomfiltermmap3-0.6.3.dist-info/top_level.txt
pybloomfiltermmap3-0.6.3.dist-info/RECORD
