Metadata-Version: 2.4
Name: pybloomfiltermmap3
Version: 0.6.3
Summary: A fast implementation of Bloom filter for Python 3 built on mmap
Home-page: https://github.com/prashnts/pybloomfiltermmap3
Author: Prashant Sinha
Author-email: Prashant Sinha <prashant@noop.pw>
License-Expression: MIT
Project-URL: Homepage, https://github.com/prashnts/pybloomfiltermmap3
Project-URL: Issues, https://github.com/prashnts/pybloomfiltermmap3/issues
Classifier: Development Status :: 4 - Beta
Classifier: Intended Audience :: Developers
Classifier: Intended Audience :: Science/Research
Classifier: Programming Language :: C
Classifier: Programming Language :: Cython
Classifier: Programming Language :: Python
Classifier: Programming Language :: Python :: 3
Classifier: Topic :: Software Development :: Libraries :: Python Modules
Requires-Python: >=3.5, <4
License-File: LICENSE
Dynamic: author
Dynamic: home-page
Dynamic: license-file
Dynamic: requires-python
